README.rst
mcloud_haproxy.py
setup.py
mcloud_plugin_haproxy.egg-info/PKG-INFO
mcloud_plugin_haproxy.egg-info/SOURCES.txt
mcloud_plugin_haproxy.egg-info/dependency_links.txt
mcloud_plugin_haproxy.egg-info/entry_points.txt
mcloud_plugin_haproxy.egg-info/requires.txt
mcloud_plugin_haproxy.egg-info/top_level.txt